LICENSE.txt
README.md
setup.py
primo/__init__.py
primo/utils.py
primo/distill/__init__.py
primo/distill/dagger.py
primo/distill/decision_tree.py
primo/distill/distiller.py
primo/model/__init__.py
primo/model/pram.py
primo/model/prdt.py
primo/model/primo.py
primo/post_optim/__init__.py
primo/post_optim/cf_explain.py
primo/post_optim/mono_constrain.py
primo/search/__init__.py
primo/search/bayes.py
primo/search/grid.py
primo/search/rand.py
pyprimo.egg-info/PKG-INFO
pyprimo.egg-info/SOURCES.txt
pyprimo.egg-info/dependency_links.txt
pyprimo.egg-info/requires.txt
pyprimo.egg-info/top_level.txt