Metadata-Version: 2.1
Name: pyprimo
Version: 0.1
Summary: Interpretable Model Optimization Framework for Learning-augmented Systems.
Home-page: https://github.com/S-Lab-System-Group/Primo
Author: Qinghao Hu
Author-email: qinghao.hu@ntu.edu.sg
License: Apache-2.0
Keywords: Computer System,Interpretability
Platform: UNKNOWN
Classifier: Topic :: System :: Operating System
Classifier: Topic :: Scientific/Engineering :: Artificial Intelligence
Classifier: Programming Language :: Python :: 3.7
Classifier: Programming Language :: Python :: 3.8
Classifier: Programming Language :: Python :: 3.9
Classifier: Programming Language :: Python :: 3.10
Requires-Python: >=3.7
License-File: LICENSE.txt
